foxessprom/__init__.py
foxessprom/auth.py
foxessprom/device.py
foxessprom/metrics.py
foxessprom/other.py
foxessprom/request.py
foxessprom/server.py
foxessprom-0.3.0.data/scripts/foxessprom
tests/__init__.py
foxessprom-0.3.0.dist-info/LICENSE
foxessprom-0.3.0.dist-info/METADATA
foxessprom-0.3.0.dist-info/WHEEL
foxessprom-0.3.0.dist-info/top_level.txt
foxessprom-0.3.0.dist-info/RECORD
