Metadata-Version: 2.1
Name: foxessprom
Version: 0.3.0
Summary: Prometheus exporter for Fox ESS Inverters (using the Fox Cloud API).
Home-page: https://github.com/andrewjw/foxessprom
Author: Andrew Wilkinson
Author-email: andrewjwilkinson@gmail.com
Classifier: Programming Language :: Python :: 3.8
Classifier: Programming Language :: Python :: 3.9
Classifier: Programming Language :: Python :: 3.10
Classifier: Programming Language :: Python :: 3.11
Classifier: Programming Language :: Python :: 3.12
Classifier: License :: OSI Approved :: GNU General Public License v3 (GPLv3)
Classifier: Operating System :: OS Independent
Requires-Python: >=3.8
License-File: LICENSE
Requires-Dist: pycodestyle ==2.12.0
Requires-Dist: coveralls ==4.0.1
Requires-Dist: python-semantic-release ==9.8.6
Requires-Dist: packaging ==24.1
Requires-Dist: wheel ==0.43.0
Requires-Dist: twine ==5.1.1
Requires-Dist: requests ==2.32.3
Requires-Dist: setuptools ==70.3.0
